ailens/main.py
ailens-0.1.0.dist-info/LICENSE
ailens-0.1.0.dist-info/METADATA
ailens-0.1.0.dist-info/WHEEL
ailens-0.1.0.dist-info/RECORD
